airflow_ecr_plugin/__init__.py
airflow_ecr_plugin/conftest.py
airflow_ecr_plugin/hooks.py
airflow_ecr_plugin/operators.py
airflow_ecr_plugin/tests/__init__.py
airflow_ecr_plugin/tests/test_hooks.py
airflow_ecr_plugin/tests/test_operators.py
airflow_ecr_plugin-0.1.3.dist-info/LICENSE
airflow_ecr_plugin-0.1.3.dist-info/WHEEL
airflow_ecr_plugin-0.1.3.dist-info/METADATA
airflow_ecr_plugin-0.1.3.dist-info/RECORD
